krypton/client/__init__.py
krypton/client/exchange/__init__.py
krypton/client/exchange/binance/__init__.py
krypton/client/exchange/binance/request.py
krypton/client/exchange/request.py
krypton/client/exchange/stream.py
krypton/client/py.typed
krypton/client/util/__init__.py
krypton/client/util/controller.py
krypton/client/worker.py
krypton_client-0.1.0.dev5.dist-info/LICENSE
krypton_client-0.1.0.dev5.dist-info/METADATA
krypton_client-0.1.0.dev5.dist-info/WHEEL
krypton_client-0.1.0.dev5.dist-info/RECORD
