Metadata-Version: 2.1
Name: krypton-client
Version: 0.1.0.dev5
Summary: Client for krypton-server and cryptocurrency exchanges
Home-page: https://github.com/nautilorg/krypton-client
License: AGPL-3.0-only
Keywords: cryptocurrency,exchange,quantitative,research,trading
Author: starecv
Author-email: starec+nautilo@mailbox.org
Requires-Python: >=3.12.1,<4.0.0
Classifier: Development Status :: 1 - Planning
Classifier: Environment :: Console
Classifier: Intended Audience :: Developers
Classifier: Intended Audience :: Financial and Insurance Industry
Classifier: License :: OSI Approved :: GNU Affero General Public License v3
Classifier: Programming Language :: Python :: 3
Classifier: Programming Language :: Python :: 3.12
Classifier: Topic :: Office/Business :: Financial
Requires-Dist: aiohttp
Requires-Dist: influxdb-client[async]
Requires-Dist: requests
Requires-Dist: websocket-client
Project-URL: Repository, https://github.com/nautilorg/krypton-client
